datajoint_connection_hub/__init__.py
datajoint_connection_hub/version.py
tests/__init__.py
tests/test_hub.py
tests/test_plugin.py
datajoint_connection_hub-0.0.4.dist-info/LICENSE
datajoint_connection_hub-0.0.4.dist-info/METADATA
datajoint_connection_hub-0.0.4.dist-info/WHEEL
datajoint_connection_hub-0.0.4.dist-info/datajoint_connection_hub.sig
datajoint_connection_hub-0.0.4.dist-info/entry_points.txt
datajoint_connection_hub-0.0.4.dist-info/top_level.txt
datajoint_connection_hub-0.0.4.dist-info/RECORD
