Metadata-Version: 2.1
Name: datajoint-connection-hub
Version: 0.0.4
Summary: Official DataJoint Python plugin for connection to DJNeuro's hosted instances.
Home-page: https://github.com/datajoint/datajoint_connection_hub-python
Author: Raphael Guzman
Author-email: raphael.h.guzman@gmail.com
License: UNKNOWN
Platform: UNKNOWN
Classifier: Programming Language :: Python :: 3
Classifier: License :: OSI Approved :: MIT License
Classifier: Operating System :: OS Independent
Requires-Dist: datajoint
Requires-Dist: requests
